Ex18/SegwayMath.sv
module SegwayMath(
    input signed [11:0] PID_cntrl,  // Signed 12-bit control from PID
    input [7:0] ss_tmr,             // Unsigned 8-bit soft-start timer
    input [11:0] steer_pot,         // 12-bit unsigned steering potentiometer
    input en_steer,                 // Steering enable signal
    input pwr_up,                   // Power up signal
    output signed [11:0] lft_spd,   // Left motor speed (signed 12-bit)
    output signed [11:0] rght_spd,  // Right motor speed (signed 12-bit)
    output too_fast                 // Over-speed detection flag
);

// Local parameters
localparam MIN_DUTY = 13'h0A8;
localparam LOW_TORQUE_BAND = 7'h2A;
localparam GAIN_MULT = 4'h4;

// Internal signals
reg signed [19:0] product;          // 20-bit product from PID_cntrl * ss_tmr
wire signed [11:0] PID_ss;          // PID scaled by soft-start timer
reg [11:0] steer_pot_limited;       // Steering pot limited to 0x200-0xE00
wire signed [11:0] steer_signed;    // Signed steering value
wire signed [12:0] steer_contribution; // 3/16 of steering value
wire signed [12:0] PID_ss_extended; // Sign-extended PID_ss to 13 bits
wire signed [12:0] lft_torque;      // Left torque before shaping
wire signed [12:0] rght_torque;     // Right torque before shaping
wire signed [12:0] lft_shaped;      // Left torque after deadzone shaping
wire signed [12:0] rght_shaped;     // Right torque after deadzone shaping
wire signed [12:0] lft_torque_comp; // Left torque compensation
wire signed [12:0] rght_torque_comp; // Right torque compensation
wire lft_in_deadzone, rght_in_deadzone; // Deadzone detection flags
wire lft_pwr_up_mux, rght_pwr_up_mux;   // Power up mux selection

// Step 1: Scale PID_cntrl by ss_tmr (soft start)
// Zero extend ss_tmr to 9 bits and cast to signed, then multiply
always_comb begin
    product = PID_cntrl * $signed({1'b0, ss_tmr});
end

// Divide by 256 (right shift by 8) to get PID_ss
assign PID_ss = product[19:8];

// Step 2: Limit steering potentiometer to range 0x200 to 0xE00
always_comb begin
    if (steer_pot < 12'h200)
        steer_pot_limited = 12'h200;
    else if (steer_pot > 12'hE00)
        steer_pot_limited = 12'hE00;
    else
        steer_pot_limited = steer_pot;
end

// Convert to signed by subtracting 0x7FF
assign steer_signed = steer_pot_limited - 12'h7FF;

// Calculate 3/16 of steering value (multiply by 3, then divide by 16)
// 3/16 can be implemented as (steer_signed * 3) >> 4
assign steer_contribution = (steer_signed * 3) >>> 4;

// Step 3: Sign extend PID_ss to 13 bits
assign PID_ss_extended = {PID_ss[11], PID_ss};

// Step 4: Add/subtract steering contribution based on en_steer
assign lft_torque = en_steer ? (PID_ss_extended + steer_contribution) : PID_ss_extended;
assign rght_torque = en_steer ? (PID_ss_extended - steer_contribution) : PID_ss_extended;

// Step 5: Deadzone compensation
// Check if torque magnitude is within LOW_TORQUE_BAND
assign lft_in_deadzone = (lft_torque[12] ? (-lft_torque) : lft_torque) < LOW_TORQUE_BAND;
assign rght_in_deadzone = (rght_torque[12] ? (-rght_torque) : rght_torque) < LOW_TORQUE_BAND;

// Calculate compensation values
assign lft_torque_comp = lft_in_deadzone ? 
    (lft_torque * $signed(GAIN_MULT)) :
    (lft_torque[12] ? (lft_torque - MIN_DUTY) : (lft_torque + MIN_DUTY));

assign rght_torque_comp = rght_in_deadzone ? 
    (rght_torque * $signed(GAIN_MULT)) :
    (rght_torque[12] ? (rght_torque - MIN_DUTY) : (rght_torque + MIN_DUTY));

// Power up mux - set to zero if not powered up
assign lft_pwr_up_mux = pwr_up;
assign rght_pwr_up_mux = pwr_up;

assign lft_shaped = lft_pwr_up_mux ? lft_torque_comp : 13'h0000;
assign rght_shaped = rght_pwr_up_mux ? rght_torque_comp : 13'h0000;

// Step 6: 12-bit signed saturation
function signed [11:0] saturate_12bit;
    input signed [12:0] value;
    begin
        if (value > $signed(12'h7FF))
            saturate_12bit = 12'h7FF;
        else if (value < $signed(12'h800))
            saturate_12bit = 12'h800;
        else
            saturate_12bit = value[11:0];
    end
endfunction

assign lft_spd = saturate_12bit(lft_shaped);
assign rght_spd = saturate_12bit(rght_shaped);

// Step 7: Over-speed detection
// too_fast is asserted if either speed exceeds 1536 (13'd1536)
// Compare 13-bit shaped values against 13-bit constant
assign too_fast = (lft_shaped > $signed(13'd1536)) || (rght_shaped > $signed(13'd1536)) ||
                  (lft_shaped < $signed(-13'd1536)) || (rght_shaped < $signed(-13'd1536));

endmodule

Ex08/Segwaymath_tb.sv
`timescale 1ns/1ps

module Segwaymath_tb();

// Testbench signals
reg signed [11:0] PID_cntrl;
reg [7:0] ss_tmr;
reg [11:0] steer_pot;
reg en_steer;
reg pwr_up;
wire signed [11:0] lft_spd;
wire signed [11:0] rght_spd;
wire too_fast;

// Clock and reset (not used by DUT but useful for simulation timing)
reg clk;

// Instantiate DUT (Device Under Test)
SegwayMath DUT (
    .PID_cntrl(PID_cntrl),
    .ss_tmr(ss_tmr),
    .steer_pot(steer_pot),
    .en_steer(en_steer),
    .pwr_up(pwr_up),
    .lft_spd(lft_spd),
    .rght_spd(rght_spd),
    .too_fast(too_fast)
);

// Clock generation for timing reference
initial begin
    clk = 0;
    forever #5 clk = ~clk; // 100MHz clock
end

// Test sequence
initial begin
    // Initialize signals
    PID_cntrl = 12'h000;
    ss_tmr = 8'h00;
    steer_pot = 12'h000;
    en_steer = 1'b0;
    pwr_up = 1'b0;
    
    $display("=== SegwayMath Testbench Starting ===");
    $display("Time\t\tPID_cntrl\tss_tmr\tsteer_pot\ten_steer\tpwr_up\tlft_spd\t\trght_spd\ttoo_fast");
    $display("====================================================================================================");
    
    // Wait for initial settling
    #10;
    
    // ==========================================
    // TEST 1: Recommended Test Scenario
    // PID_cntrl starts at 12'h5FF, ss_tmr ramps 0 to 8'hFF
    // Then PID_cntrl ramps from 12'h5FF to 12'hE00
    // steer_en = 0, pwr_up = 1
    // ==========================================
    
    $display("\n=== TEST 1: PID Control with Soft Start ===");
    
    // Initial conditions for Test 1
    PID_cntrl = 12'h5FF;  // +1535
    ss_tmr = 8'h00;
    steer_pot = 12'h7FF;  // Mid-range, but not used since en_steer = 0
    en_steer = 1'b0;
    pwr_up = 1'b1;
    
    #10;
    $display("%0t\t\t%h\t\t%h\t%h\t\t%b\t\t%b\t%d\t\t%d\t\t%b", 
             $time, PID_cntrl, ss_tmr, steer_pot, en_steer, pwr_up, lft_spd, rght_spd, too_fast);
    
    // Ramp ss_tmr from 0 to 0xFF slowly for smooth ramping
    $display("\n--- Ramping ss_tmr from 0x00 to 0xFF ---");
    for (int i = 0; i <= 255; i = i + 4) begin
        ss_tmr = i[7:0];
        #20;  // Slower timing for smoother waves
        if (i % 16 == 0 || i == 255) begin
            $display("%0t\t\t%h\t\t%h\t%h\t\t%b\t\t%b\t%d\t\t%d\t\t%b", 
                     $time, PID_cntrl, ss_tmr, steer_pot, en_steer, pwr_up, lft_spd, rght_spd, too_fast);
        end
    end
    
    // Now ramp PID_cntrl from 12'h5FF (+1535) to 12'hE00 (-512) slowly
    $display("\n--- Ramping PID_cntrl from 0x5FF (+1535) to 0xE00 (-512) ---");
    ss_tmr = 8'hFF; // Keep ss_tmr at maximum
    
    // Use a more gradual ramp with smaller steps
    for (int i = 0; i <= 64; i++) begin
        // Linear interpolation from 0x5FF to 0xE00
        // 0x5FF = 1535, 0xE00 = -512 (in 12-bit signed)
        // We need to go from +1535 to -512, which is a range of 2047
        automatic int signed start_val = 1535;
        automatic int signed end_val = -512;
        automatic int signed current_val = start_val + ((end_val - start_val) * i / 64);
        PID_cntrl = current_val[11:0];
        
        #20;  // Slower timing for smoother waves
        if (i % 8 == 0 || i == 64) begin
            $display("%0t\t\t%h\t\t%h\t%h\t\t%b\t\t%b\t%d\t\t%d\t\t%b", 
                     $time, PID_cntrl, ss_tmr, steer_pot, en_steer, pwr_up, lft_spd, rght_spd, too_fast);
        end
    end
    
    #100; // Wait between tests
    
    // ==========================================
    // TEST 2: Steering Test Scenario  
    // PID_cntrl starts at 12'h3FF (1023) and ramps to 12'hC00 (-1024)
    // ss_tmr stays at 8'hFF
    // steer_pot ramps from 12'h000 to 12'hFFE
    // steer_en = 1, pwr_up falls at end
    // ==========================================
    
    $display("\n\n=== TEST 2: Steering Control Test ===");
    
    // Initial conditions for Test 2
    PID_cntrl = 12'h3FF;  // +1023
    ss_tmr = 8'hFF;       // Maximum throughout
    steer_pot = 12'h000;
    en_steer = 1'b1;      // Enable steering
    pwr_up = 1'b1;
    
    #10;
    $display("%0t\t\t%h\t\t%h\t%h\t\t%b\t\t%b\t%d\t\t%d\t\t%b", 
             $time, PID_cntrl, ss_tmr, steer_pot, en_steer, pwr_up, lft_spd, rght_spd, too_fast);
    
    // Sweep both PID_cntrl and steer_pot simultaneously with smooth ramping
    $display("\n--- Sweeping PID_cntrl (0x3FF to 0xC00) and steer_pot (0x000 to 0xFFE) ---");
    
    for (int step = 0; step <= 64; step++) begin
        // Calculate PID_cntrl value (from 0x3FF to 0xC00)
        // Linear interpolation for smooth ramping
        automatic int signed start_pid = 1023;  // 0x3FF
        automatic int signed end_pid = -1024;   // 0xC00 in signed 12-bit
        automatic int signed current_pid = start_pid + ((end_pid - start_pid) * step / 64);
        PID_cntrl = current_pid[11:0];
        
        // Calculate steer_pot value (from 0x000 to 0xFFE) - smooth linear ramp
        steer_pot = (12'hFFE * step / 64);
        
        #15;  // Moderate timing for smooth waves
        
        // Print every 8th step to keep output manageable
        if (step % 8 == 0 || step == 64) begin
            $display("%0t\t\t%h\t\t%h\t%h\t\t%b\t\t%b\t%d\t\t%d\t\t%b", 
                     $time, PID_cntrl, ss_tmr, steer_pot, en_steer, pwr_up, lft_spd, rght_spd, too_fast);
        end
    end
    
    // Test power down at the end
    $display("\n--- Testing power down ---");
    #10;
    pwr_up = 1'b0;  // Power down
    #10;
    $display("%0t\t\t%h\t\t%h\t%h\t\t%b\t\t%b\t%d\t\t%d\t\t%b", 
             $time, PID_cntrl, ss_tmr, steer_pot, en_steer, pwr_up, lft_spd, rght_spd, too_fast);
    
    // ==========================================
    // Additional Edge Case Tests
    // ==========================================
    
    $display("\n\n=== ADDITIONAL EDGE CASE TESTS ===");
    
    // Test saturation cases
    pwr_up = 1'b1;
    en_steer = 1'b0;
    ss_tmr = 8'hFF;
    
    // Test maximum positive PID_cntrl
    PID_cntrl = 12'h7FF;  // Maximum positive
    #10;
    $display("Max Positive PID: %0t\t%h\t\t%h\t%h\t\t%b\t\t%b\t%d\t\t%d\t\t%b", 
             $time, PID_cntrl, ss_tmr, steer_pot, en_steer, pwr_up, lft_spd, rght_spd, too_fast);
    
    // Test maximum negative PID_cntrl  
    PID_cntrl = 12'h800;  // Maximum negative
    #10;
    $display("Max Negative PID: %0t\t%h\t\t%h\t%h\t\t%b\t\t%b\t%d\t\t%d\t\t%b", 
             $time, PID_cntrl, ss_tmr, steer_pot, en_steer, pwr_up, lft_spd, rght_spd, too_fast);
    
    // Test steering saturation
    en_steer = 1'b1;
    PID_cntrl = 12'h000;  // Zero PID to see steering effect clearly
    
    steer_pot = 12'h000;  // Minimum steering
    #10;
    $display("Min Steering:     %0t\t%h\t\t%h\t%h\t\t%b\t\t%b\t%d\t\t%d\t\t%b", 
             $time, PID_cntrl, ss_tmr, steer_pot, en_steer, pwr_up, lft_spd, rght_spd, too_fast);
    
    steer_pot = 12'hFFF;  // Maximum steering
    #10;
    $display("Max Steering:     %0t\t%h\t\t%h\t%h\t\t%b\t\t%b\t%d\t\t%d\t\t%b", 
             $time, PID_cntrl, ss_tmr, steer_pot, en_steer, pwr_up, lft_spd, rght_spd, too_fast);
    
    #100;
    
    $display("\n=== SegwayMath Testbench Complete ===");
    $finish;
end

// Monitor for too_fast assertions
initial begin
    forever begin
        @(posedge too_fast);
        $display("*** WARNING: too_fast asserted at time %0t ***", $time);
    end
end

// Optional: Generate VCD file for waveform viewing
initial begin
    $dumpfile("segwaymath_tb.vcd");
    $dumpvars(0, Segwaymath_tb);
end

endmodule

Ex08/segwaymath_tb.vcd
$date
	Wed Sep 24 10:52:59 2025
$end
$version
	Questa Intel Starter FPGA Edition Version 2024.3
$end
$timescale
	1ps
$end

$scope module Segwaymath_tb $end
$var reg 12 ! PID_cntrl [11:0] $end
$var reg 8 " ss_tmr [7:0] $end
$var reg 12 # steer_pot [11:0] $end
$var reg 1 $ en_steer $end
$var reg 1 % pwr_up $end
$var wire 1 & lft_spd [11] $end
$var wire 1 ' lft_spd [10] $end
$var wire 1 ( lft_spd [9] $end
$var wire 1 ) lft_spd [8] $end
$var wire 1 * lft_spd [7] $end
$var wire 1 + lft_spd [6] $end
$var wire 1 , lft_spd [5] $end
$var wire 1 - lft_spd [4] $end
$var wire 1 . lft_spd [3] $end
$var wire 1 / lft_spd [2] $end
$var wire 1 0 lft_spd [1] $end
$var wire 1 1 lft_spd [0] $end
$var wire 1 2 rght_spd [11] $end
$var wire 1 3 rght_spd [10] $end
$var wire 1 4 rght_spd [9] $end
$var wire 1 5 rght_spd [8] $end
$var wire 1 6 rght_spd [7] $end
$var wire 1 7 rght_spd [6] $end
$var wire 1 8 rght_spd [5] $end
$var wire 1 9 rght_spd [4] $end
$var wire 1 : rght_spd [3] $end
$var wire 1 ; rght_spd [2] $end
$var wire 1 < rght_spd [1] $end
$var wire 1 = rght_spd [0] $end
$var wire 1 > too_fast $end
$var reg 1 ? clk $end

$scope module DUT $end
$var parameter 13 @ MIN_DUTY $end
$var parameter 7 A LOW_TORQUE_BAND $end
$var parameter 4 B GAIN_MULT $end
$var wire 1 C PID_cntrl [11] $end
$var wire 1 D PID_cntrl [10] $end
$var wire 1 E PID_cntrl [9] $end
$var wire 1 F PID_cntrl [8] $end
$var wire 1 G PID_cntrl [7] $end
$var wire 1 H PID_cntrl [6] $end
$var wire 1 I PID_cntrl [5] $end
$var wire 1 J PID_cntrl [4] $end
$var wire 1 K PID_cntrl [3] $end
$var wire 1 L PID_cntrl [2] $end
$var wire 1 M PID_cntrl [1] $end
$var wire 1 N PID_cntrl [0] $end
$var wire 1 O ss_tmr [7] $end
$var wire 1 P ss_tmr [6] $end
$var wire 1 Q ss_tmr [5] $end
$var wire 1 R ss_tmr [4] $end
$var wire 1 S ss_tmr [3] $end
$var wire 1 T ss_tmr [2] $end
$var wire 1 U ss_tmr [1] $end
$var wire 1 V ss_tmr [0] $end
$var wire 1 W steer_pot [11] $end
$var wire 1 X steer_pot [10] $end
$var wire 1 Y steer_pot [9] $end
$var wire 1 Z steer_pot [8] $end
$var wire 1 [ steer_pot [7] $end
$var wire 1 \ steer_pot [6] $end
$var wire 1 ] steer_pot [5] $end
$var wire 1 ^ steer_pot [4] $end
$var wire 1 _ steer_pot [3] $end
$var wire 1 ` steer_pot [2] $end
$var wire 1 a steer_pot [1] $end
$var wire 1 b steer_pot [0] $end
$var wire 1 c en_steer $end
$var wire 1 d pwr_up $end
$var wire 1 & lft_spd [11] $end
$var wire 1 ' lft_spd [10] $end
$var wire 1 ( lft_spd [9] $end
$var wire 1 ) lft_spd [8] $end
$var wire 1 * lft_spd [7] $end
$var wire 1 + lft_spd [6] $end
$var wire 1 , lft_spd [5] $end
$var wire 1 - lft_spd [4] $end
$var wire 1 . lft_spd [3] $end
$var wire 1 / lft_spd [2] $end
$var wire 1 0 lft_spd [1] $end
$var wire 1 1 lft_spd [0] $end
$var wire 1 2 rght_spd [11] $end
$var wire 1 3 rght_spd [10] $end
$var wire 1 4 rght_spd [9] $end
$var wire 1 5 rght_spd [8] $end
$var wire 1 6 rght_spd [7] $end
$var wire 1 7 rght_spd [6] $end
$var wire 1 8 rght_spd [5] $end
$var wire 1 9 rght_spd [4] $end
$var wire 1 : rght_spd [3] $end
$var wire 1 ; rght_spd [2] $end
$var wire 1 < rght_spd [1] $end
$var wire 1 = rght_spd [0] $end
$var wire 1 > too_fast $end
$var reg 20 e product [19:0] $end
$var wire 1 f PID_ss [11] $end
$var wire 1 g PID_ss [10] $end
$var wire 1 h PID_ss [9] $end
$var wire 1 i PID_ss [8] $end
$var wire 1 j PID_ss [7] $end
$var wire 1 k PID_ss [6] $end
$var wire 1 l PID_ss [5] $end
$var wire 1 m PID_ss [4] $end
$var wire 1 n PID_ss [3] $end
$var wire 1 o PID_ss [2] $end
$var wire 1 p PID_ss [1] $end
$var wire 1 q PID_ss [0] $end
$var reg 12 r steer_pot_limited [11:0] $end
$var wire 1 s steer_signed [11] $end
$var wire 1 t steer_signed [10] $end
$var wire 1 u steer_signed [9] $end
$var wire 1 v steer_signed [8] $end
$var wire 1 w steer_signed [7] $end
$var wire 1 x steer_signed [6] $end
$var wire 1 y steer_signed [5] $end
$var wire 1 z steer_signed [4] $end
$var wire 1 { steer_signed [3] $end
$var wire 1 | steer_signed [2] $end
$var wire 1 } steer_signed [1] $end
$var wire 1 ~ steer_signed [0] $end
$var wire 1 !! steer_contribution [12] $end
$var wire 1 "! steer_contribution [11] $end
$var wire 1 #! steer_contribution [10] $end
$var wire 1 $! steer_contribution [9] $end
$var wire 1 %! steer_contribution [8] $end
$var wire 1 &! steer_contribution [7] $end
$var wire 1 '! steer_contribution [6] $end
$var wire 1 (! steer_contribution [5] $end
$var wire 1 )! steer_contribution [4] $end
$var wire 1 *! steer_contribution [3] $end
$var wire 1 +! steer_contribution [2] $end
$var wire 1 ,! steer_contribution [1] $end
$var wire 1 -! steer_contribution [0] $end
$var wire 1 .! PID_ss_extended [12] $end
$var wire 1 /! PID_ss_extended [11] $end
$var wire 1 0! PID_ss_extended [10] $end
$var wire 1 1! PID_ss_extended [9] $end
$var wire 1 2! PID_ss_extended [8] $end
$var wire 1 3! PID_ss_extended [7] $end
$var wire 1 4! PID_ss_extended [6] $end
$var wire 1 5! PID_ss_extended [5] $end
$var wire 1 6! PID_ss_extended [4] $end
$var wire 1 7! PID_ss_extended [3] $end
$var wire 1 8! PID_ss_extended [2] $end
$var wire 1 9! PID_ss_extended [1] $end
$var wire 1 :! PID_ss_extended [0] $end
$var wire 1 ;! lft_torque [12] $end
$var wire 1 <! lft_torque [11] $end
$var wire 1 =! lft_torque [10] $end
$var wire 1 >! lft_torque [9] $end
$var wire 1 ?! lft_torque [8] $end
$var wire 1 @! lft_torque [7] $end
$var wire 1 A! lft_torque [6] $end
$var wire 1 B! lft_torque [5] $end
$var wire 1 C! lft_torque [4] $end
$var wire 1 D! lft_torque [3] $end
$var wire 1 E! lft_torque [2] $end
$var wire 1 F! lft_torque [1] $end
$var wire 1 G! lft_torque [0] $end
$var wire 1 H! rght_torque [12] $end
$var wire 1 I! rght_torque [11] $end
$var wire 1 J! rght_torque [10] $end
$var wire 1 K! rght_torque [9] $end
$var wire 1 L! rght_torque [8] $end
$var wire 1 M! rght_torque [7] $end
$var wire 1 N! rght_torque [6] $end
$var wire 1 O! rght_torque [5] $end
$var wire 1 P! rght_torque [4] $end
$var wire 1 Q! rght_torque [3] $end
$var wire 1 R! rght_torque [2] $end
$var wire 1 S! rght_torque [1] $end
$var wire 1 T! rght_torque [0] $end
$var wire 1 U! lft_shaped [12] $end
$var wire 1 V! lft_shaped [11] $end
$var wire 1 W! lft_shaped [10] $end
$var wire 1 X! lft_shaped [9] $end
$var wire 1 Y! lft_shaped [8] $end
$var wire 1 Z! lft_shaped [7] $end
$var wire 1 [! lft_shaped [6] $end
$var wire 1 \! lft_shaped [5] $end
$var wire 1 ]! lft_shaped [4] $end
$var wire 1 ^! lft_shaped [3] $end
$var wire 1 _! lft_shaped [2] $end
$var wire 1 `! lft_shaped [1] $end
$var wire 1 a! lft_shaped [0] $end
$var wire 1 b! rght_shaped [12] $end
$var wire 1 c! rght_shaped [11] $end
$var wire 1 d! rght_shaped [10] $end
$var wire 1 e! rght_shaped [9] $end
$var wire 1 f! rght_shaped [8] $end
$var wire 1 g! rght_shaped [7] $end
$var wire 1 h! rght_shaped [6] $end
$var wire 1 i! rght_shaped [5] $end
$var wire 1 j! rght_shaped [4] $end
$var wire 1 k! rght_shaped [3] $end
$var wire 1 l! rght_shaped [2] $end
$var wire 1 m! rght_shaped [1] $end
$var wire 1 n! rght_shaped [0] $end
$var wire 1 o! lft_torque_comp [12] $end
$var wire 1 p! lft_torque_comp [11] $end
$var wire 1 q! lft_torque_comp [10] $end
$var wire 1 r! lft_torque_comp [9] $end
$var wire 1 s! lft_torque_comp [8] $end
$var wire 1 t! lft_torque_comp [7] $end
$var wire 1 u! lft_torque_comp [6] $end
$var wire 1 v! lft_torque_comp [5] $end
$var wire 1 w! lft_torque_comp [4] $end
$var wire 1 x! lft_torque_comp [3] $end
$var wire 1 y! lft_torque_comp [2] $end
$var wire 1 z! lft_torque_comp [1] $end
$var wire 1 {! lft_torque_comp [0] $end
$var wire 1 |! rght_torque_comp [12] $end
$var wire 1 }! rght_torque_comp [11] $end
$var wire 1 ~! rght_torque_comp [10] $end
$var wire 1 !" rght_torque_comp [9] $end
$var wire 1 "" rght_torque_comp [8] $end
$var wire 1 #" rght_torque_comp [7] $end
$var wire 1 $" rght_torque_comp [6] $end
$var wire 1 %" rght_torque_comp [5] $end
$var wire 1 &" rght_torque_comp [4] $end
$var wire 1 '" rght_torque_comp [3] $end
$var wire 1 (" rght_torque_comp [2] $end
$var wire 1 )" rght_torque_comp [1] $end
$var wire 1 *" rght_torque_comp [0] $end
$var wire 1 +" lft_in_deadzone $end
$var wire 1 ," rght_in_deadzone $end
$var wire 1 -" lft_pwr_up_mux $end
$var wire 1 ." rght_pwr_up_mux $end

$scope function saturate_12bit $end
$var reg 12 /" saturate_12bit [11:0] $end
$var reg 13 0" value [12:0] $end
$upscope $end
$upscope $end
$upscope $end
$enddefinitions $end
#0
$dumpvars
b0 !
b0 "
b0 #
0$
0%
0?
b0 e
b1000000000 r
b0 /"
b0 0"
b10101000 @
b101010 A
b100 B
01
00
0/
0.
0-
0,
0+
0*
0)
0(
0'
0&
0=
0<
0;
0:
09
08
07
06
05
04
03
02
0>
0q
0p
0o
0n
0m
0l
0k
0j
0i
0h
0g
0f
1~
0}
0|
0{
0z
0y
0x
0w
0v
1u
0t
1s
0-!
0,!
0+!
0*!
0)!
1(!
1'!
1&!
0%!
1$!
1#!
1"!
1!!
0:!
09!
08!
07!
06!
05!
04!
03!
02!
01!
00!
0/!
0.!
0G!
0F!
0E!
0D!
0C!
0B!
0A!
0@!
0?!
0>!
0=!
0<!
0;!
0T!
0S!
0R!
0Q!
0P!
0O!
0N!
0M!
0L!
0K!
0J!
0I!
0H!
0a!
0`!
0_!
0^!
0]!
0\!
0[!
0Z!
0Y!
0X!
0W!
0V!
0U!
0n!
0m!
0l!
0k!
0j!
0i!
0h!
0g!
0f!
0e!
0d!
0c!
0b!
0{!
0z!
0y!
0x!
0w!
0v!
0u!
0t!
0s!
0r!
0q!
0p!
0o!
0*"
0)"
0("
0'"
0&"
0%"
0$"
0#"
0""
0!"
0~!
0}!
0|!
1+"
1,"
0-"
0."
0d
0c
0b
0a
0`
0_
0^
0]
0\
0[
0Z
0Y
0X
0W
0V
0U
0T
0S
0R
0Q
0P
0O
0N
0M
0L
0K
0J
0I
0H
0G
0F
0E
0D
0C
$end
#5000
1?
#10000
b10111111111 !
b11111111111 #
1%
0?
1d
1-"
1."
1b
1a
1`
1_
1^
1]
1\
1[
1Z
1Y
1X
1N
1M
1L
1K
1J
1I
1H
1G
1F
1D
b11111111111 r
0~
0u
0s
0(!
0'!
0&!
0$!
0#!
0"!
0!!
#15000
1?
#20000
0?
#25000
1?
#30000
0?
#35000
1?
#40000
b100 "
0?
1T
b1011111111100 e
1q
1p
1o
1m
1:!
19!
18!
16!
1G!
1F!
1E!
1C!
1T!
1S!
1R!
1P!
1y!
1x!
1w!
1u!
1("
1'"
1&"
1$"
1l!
1k!
1j!
1h!
1_!
1^!
1]!
1[!
b1011100 0"
b1011100 /"
1;
1:
19
17
1/
1.
1-
1+
#45000
1?
#50000
0?
#55000
1?
#60000
b1000 "
0?
0T
1S
b10111111111000 e
1n
0m
1l
17!
06!
15!
1D!
0C!
1B!
1Q!
0P!
1O!
0,"
0+"
1v!
0u!
1t!
1%"
0$"
1#"
1i!
0h!
1g!
1\!
0[!
1Z!
1{!
1z!
0x!
0v!
1u!
1*"
1)"
0'"
0%"
1$"
b10111100 0"
b10111100 /"
18
07
16
1,
0+
1*
1n!
1m!
0k!
0i!
1h!
1a!
1`!
0^!
0\!
1[!
b11010111 0"
b11010111 /"
1=
1<
0:
08
17
11
10
0.
0,
1+
#65000
1?
#70000
0?
#75000
1?
#80000
b1100 "
0?
1T
b100011111110100 e
0n
0l
1k
07!
05!
14!
0D!
0B!
1A!
0Q!
0O!
1N!
1x!
0w!
1v!
1'"
0&"
1%"
1k!
0j!
1i!
1^!
0]!
1\!
b11101111 0"
b11101111 /"
1:
09
18
1.
0-
1,
#85000
1?
#90000
0?
#95000
1?
#100000
b10000 "
0?
0T
0S
1R
b101111111110000 e
1n
1m
17!
16!
1D!
1C!
1Q!
1P!
0x!
0v!
0u!
0t!
1s!
0'"
0%"
0$"
0#"
1""
0k!
0i!
0h!
0g!
1f!
0^!
0\!
0[!
0Z!
1Y!
b100000111 0"
b100000111 /"
0:
08
07
06
15
0.
0,
0+
0*
1)
#105000
1?
#110000
0?
#115000
1?
#120000
b10100 "
0?
1T
b111011111101100 e
0n
1l
07!
15!
0D!
1B!
0Q!
1O!
1x!
1w!
1'"
1&"
1k!
1j!
1^!
1]!
b100011111 0"
b100011111 /"
1:
19
1.
1-
#125000
1?
#130000
0?
#135000
1?
#140000
b11000 "
0?
0T
1S
b1000111111101000 e
1n
0m
0l
0k
1j
17!
06!
05!
04!
13!
1D!
0C!
0B!
0A!
1@!
1Q!
0P!
0O!
0N!
1M!
0x!
1v!
0'"
1%"
0k!
1i!
0^!
1\!
b100110111 0"
b100110111 /"
0:
18
0.
1,
#145000
1?
#150000
0?
#155000
1?
#160000
b11100 "
0?
1T
b1010011111100100 e
0n
1l
07!
15!
0D!
1B!
0Q!
1O!
1x!
0w!
0v!
1u!
1'"
0&"
0%"
1$"
1k!
0j!
0i!
1h!
1^!
0]!
0\!
1[!
b101001111 0"
b101001111 /"
1:
09
08
17
1.
0-
0,
1+
#165000
1?
#170000
0?
#175000
1?
#180000
b100000 "
0?
0T
0S
0R
1Q
b1011111111100000 e
1n
1m
17!
16!
1D!
1C!
1Q!
1P!
0x!
1v!
0'"
1%"
0k!
1i!
0^!
1\!
b101100111 0"
b101100111 /"
0:
18
0.
1,
#185000
1?
#190000
0?
#195000
1?
#200000
b100100 "
0?
1T
b1101011111011100 e
0n
0l
1k
07!
05!
14!
0D!
0B!
1A!
0Q!
0O!
1N!
1x!
1w!
1'"
1&"
1k!
1j!
1^!
1]!
b101111111 0"
b101111111 /"
1:
19
1.
1-
#205000
1?
#210000
0?
#215000
1?
#220000
b101000 "
0?
0T
1S
b1110111111011000 e
1n
0m
1l
17!
06!
15!
1D!
0C!
1B!
1Q!
0P!
1O!
0x!
0v!
0u!
1t!
0'"
0%"
0$"
1#"
0k!
0i!
0h!
1g!
0^!
0\!
0[!
1Z!
b110010111 0"
b110010111 /"
0:
08
07
16
0.
0,
0+
1*
#225000
1?
#230000
0?
#235000
1?
#240000
b101100 "
0?
1T
b10000011111010100 e
0n
0l
0k
0j
1i
07!
05!
04!
03!
12!
0D!
0B!
0A!
0@!
1?!
0Q!
0O!
0N!
0M!
1L!
1x!
0w!
1v!
1'"
0&"
1%"
1k!
0j!
1i!
1^!
0]!
1\!
b110101111 0"
b110101111 /"
1:
09
18
1.
0-
1,
#245000
1?
#250000
0?
#255000
1?
#260000
b110000 "
0?
0T
0S
1R
b10001111111010000 e
1n
1m
17!
16!
1D!
1C!
1Q!
1P!
0x!
0v!
1u!
0'"
0%"
1$"
0k!
0i!
1h!
0^!
0\!
1[!
b111000111 0"
b111000111 /"
0:
08
17
0.
0,
1+
#265000
1?
#270000
0?
#275000
1?
#280000
b110100 "
0?
1T
b10011011111001100 e
0n
1l
07!
15!
0D!
1B!
0Q!
1O!
1x!
1w!
1'"
1&"
1k!
1j!
1^!
1]!
b111011111 0"
b111011111 /"
1:
19
1.
1-
#285000
1?
#290000
0?
#295000
1?
#300000
b111000 "
0?
0T
1S
b10100111111001000 e
1n
0m
0l
1k
17!
06!
05!
14!
1D!
0C!
0B!
1A!
1Q!
0P!
0O!
1N!
0x!
1v!
0'"
1%"
0k!
1i!
0^!
1\!
b111110111 0"
b111110111 /"
0:
18
0.
1,
#305000
1?
#310000
0?
#315000
1?
#320000
b111100 "
0?
1T
b10110011111000100 e
0n
1l
07!
15!
0D!
1B!
0Q!
1O!
1x!
0w!
0v!
0u!
0t!
0s!
1r!
1'"
0&"
0%"
0$"
0#"
0""
1!"
1k!
0j!
0i!
0h!
0g!
0f!
1e!
1^!
0]!
0\!
0[!
0Z!
0Y!
1X!
b1000001111 0"
b1000001111 /"
1:
09
08
07
06
05
14
1.
0-
0,
0+
0*
0)
1(
#325000
1?
#330000
0?
#335000
1?
#340000
b1000000 "
0?
0T
0S
0R
0Q
1P
b10111111111000000 e
1n
1m
17!
16!
1D!
1C!
1Q!
1P!
0x!
1v!
0'"
1%"
0k!
1i!
0^!
1\!
b1000100111 0"
b1000100111 /"
0:
18
0.
1,
#345000
1?
#350000
0?
#355000
1?
#360000
b1000100 "
0?
1T
b11001011110111100 e
0n
0l
0k
1j
07!
05!
04!
13!
0D!
0B!
0A!
1@!
0Q!
0O!
0N!
1M!
1x!
1w!
1'"
1&"
1k!
1j!
1^!
1]!
b1000111111 0"
b1000111111 /"
1:
19
1.
1-
#365000
1?
#370000
0?
#375000
1?
#380000
b1001000 "
0?
0T
1S
b11010111110111000 e
1n
0m
1l
17!
06!
15!
1D!
0C!
1B!
1Q!
0P!
1O!
0x!
0v!
1u!
0'"
0%"
1$"
0k!
0i!
1h!
0^!
0\!
1[!
b1001010111 0"
b1001010111 /"
0:
08
17
0.
0,
1+
#385000
1?
#390000
0?
#395000
1?
