Ex10/PWM11.sv
module PWM11(
    input clk,              // 50MHz system clock
    input rst_n,            // Asynchronous active low reset
    input [10:0] duty,      // Specifies duty cycle (unsigned 11-bit)
    output PWM1,            // Complementary glitch free PWM signals
    output PWM2,            // with non-overlap
    output PWM_synch,       // Use to synch changes in duty
    output ovr_I_blank      // Used to blank out over current mitigation
);

// Local parameter for non-overlap time
localparam NONOVERLAP = 11'h040;  // 64 clock cycles of non-overlap

// 11-bit free-running counter
reg [10:0] cnt;

// Counter logic - counts from 0 to 2047 then rolls over
always @(posedge clk, negedge rst_n) begin
    if (!rst_n)
        cnt <= 11'h000;
    else
        cnt <= cnt + 1;
end

// PWM_synch signal - high when counter is all zeros
assign PWM_synch = ~|cnt;  // NOR of all bits (true when cnt == 0)

// Set/Reset combinational logic for PWM signals
wire set_PWM1, reset_PWM1;
wire set_PWM2, reset_PWM2;

// PWM1 logic: runs from NONOVERLAP to duty
assign set_PWM1 = (cnt >= NONOVERLAP);
assign reset_PWM1 = (cnt >= duty);

// PWM2 logic: runs from duty+NONOVERLAP to 2047 (wraps to 0)
assign set_PWM2 = (cnt >= (duty + NONOVERLAP));
assign reset_PWM2 = ~|cnt;  // Reset when counter rolls over to 0

// SR Flip-flops for PWM1 and PWM2
reg PWM1_reg, PWM2_reg;

// PWM1 SR flip-flop
always @(posedge clk, negedge rst_n) begin
    if (!rst_n)
        PWM1_reg <= 1'b0;
    else if (reset_PWM1)
        PWM1_reg <= 1'b0;
    else if (set_PWM1)
        PWM1_reg <= 1'b1;
end

// PWM2 SR flip-flop  
always @(posedge clk, negedge rst_n) begin
    if (!rst_n)
        PWM2_reg <= 1'b0;
    else if (reset_PWM2)
        PWM2_reg <= 1'b0;
    else if (set_PWM2)
        PWM2_reg <= 1'b1;
end

// Output assignments
assign PWM1 = PWM1_reg;
assign PWM2 = PWM2_reg;

// Over current blanking signal
// Blank during first 128 clocks of either PWM1 or PWM2 pulse
assign ovr_I_blank = ((cnt >= NONOVERLAP) && (cnt < (NONOVERLAP + 128))) ||
                     ((cnt >= (duty + NONOVERLAP)) && (cnt < (duty + NONOVERLAP + 128)));

endmodule

Ex10/PWM11_tb.sv
module PWM11_tb();

// Testbench signals
reg clk, rst_n;
reg [10:0] duty;
wire PWM1, PWM2, PWM_synch, ovr_I_blank;

// Instantiate the PWM11 module
PWM11 iDUT (
    .clk(clk),
    .rst_n(rst_n),
    .duty(duty),
    .PWM1(PWM1),
    .PWM2(PWM2),
    .PWM_synch(PWM_synch),
    .ovr_I_blank(ovr_I_blank)
);

// Clock generation (50MHz = 20ns period)
initial begin
    clk = 0;
    forever #10 clk = ~clk;  // 50MHz clock
end

// Test stimulus
initial begin
    // Initialize signals
    rst_n = 0;
    duty = 11'h000;
    
    // Apply reset
    @(posedge clk);
    @(negedge clk);
    rst_n = 1;
    
    // Test Case 1: 50% duty cycle (duty = 0x400 = 1024)
    $display("Testing 50%% duty cycle (duty = 0x400)");
    duty = 11'h400;  // 1024 decimal
    repeat(4096) @(posedge clk);  // Run for 2 full PWM cycles
    
    // Test Case 2: 25% duty cycle (duty = 0x200 = 512) 
    $display("Testing 25%% duty cycle (duty = 0x200)");
    duty = 11'h200;  // 512 decimal
    repeat(4096) @(posedge clk);  // Run for 2 full PWM cycles
    
    // Test Case 3: 75% duty cycle (duty = 0x600 = 1536)
    $display("Testing 75%% duty cycle (duty = 0x600)");
    duty = 11'h600;  // 1536 decimal
    repeat(4096) @(posedge clk);  // Run for 2 full PWM cycles
    
    // Test Case 4: Very low duty cycle (less than NONOVERLAP)
    $display("Testing very low duty cycle (duty = 0x020)");
    duty = 11'h020;  // 32 decimal (less than NONOVERLAP = 64)
    repeat(4096) @(posedge clk);  // Run for 2 full PWM cycles
    
    // Test Case 5: Very high duty cycle
    $display("Testing very high duty cycle (duty = 0x780)");
    duty = 11'h780;  // 1920 decimal
    repeat(4096) @(posedge clk);  // Run for 2 full PWM cycles
    
    $display("Simulation completed");
    $stop;
end

// Generate VCD file for waveform viewing
initial begin
    $dumpfile("PWM11_tb.vcd");
    $dumpvars(0, PWM11_tb);
end

// Display key signal changes at specific times
always @(posedge PWM_synch) begin
    $display("Time=%0t: PWM cycle start - duty=%h PWM1=%b PWM2=%b ovr_I_blank=%b", 
             $time, duty, PWM1, PWM2, ovr_I_blank);
end

endmodule

Ex10/PWM11_tb.vcd
$date
	Mon Sep 29 10:24:40 2025
$end
$version
	Questa Intel Starter FPGA Edition Version 2024.3
$end
$timescale
	1ns
$end

$scope module PWM11_tb $end
$var reg 1 ! clk $end
$var reg 1 " rst_n $end
$var reg 11 # duty [10:0] $end
$var wire 1 $ PWM1 $end
$var wire 1 % PWM2 $end
$var wire 1 & PWM_synch $end
$var wire 1 ' ovr_I_blank $end

$scope module iDUT $end
$var parameter 11 ( NONOVERLAP $end
$var wire 1 ) clk $end
$var wire 1 * rst_n $end
$var wire 1 + duty [10] $end
$var wire 1 , duty [9] $end
$var wire 1 - duty [8] $end
$var wire 1 . duty [7] $end
$var wire 1 / duty [6] $end
$var wire 1 0 duty [5] $end
$var wire 1 1 duty [4] $end
$var wire 1 2 duty [3] $end
$var wire 1 3 duty [2] $end
$var wire 1 4 duty [1] $end
$var wire 1 5 duty [0] $end
$var wire 1 $ PWM1 $end
$var wire 1 % PWM2 $end
$var wire 1 & PWM_synch $end
$var wire 1 ' ovr_I_blank $end
$var reg 11 6 cnt [10:0] $end
$var wire 1 7 set_PWM1 $end
$var wire 1 8 reset_PWM1 $end
$var wire 1 9 set_PWM2 $end
$var wire 1 : reset_PWM2 $end
$var reg 1 ; PWM1_reg $end
$var reg 1 < PWM2_reg $end
$upscope $end
$upscope $end
$enddefinitions $end
#0
$dumpvars
0!
0"
b0 #
b0 6
0;
0<
b1000000 (
0$
0%
1&
0'
07
18
09
1:
05
04
03
02
01
00
0/
0.
0-
0,
0+
0*
0)
$end
#10
1!
1)
#20
0!
0)
1"
b10000000000 #
1+
08
1*
#30
1!
1)
b1 6
0:
0&
#40
0!
0)
#50
1!
1)
b10 6
#60
0!
0)
#70
1!
1)
b11 6
#80
0!
0)
#90
1!
1)
b100 6
#100
0!
0)
#110
1!
1)
b101 6
#120
0!
0)
#130
1!
1)
b110 6
#140
0!
0)
#150
1!
1)
b111 6
#160
0!
0)
#170
1!
1)
b1000 6
#180
0!
0)
#190
1!
1)
b1001 6
#200
0!
0)
#210
1!
1)
b1010 6
#220
0!
0)
#230
1!
1)
b1011 6
#240
0!
0)
#250
1!
1)
b1100 6
#260
0!
0)
#270
1!
1)
b1101 6
#280
0!
0)
#290
1!
1)
b1110 6
#300
0!
0)
#310
1!
1)
b1111 6
#320
0!
0)
#330
1!
1)
b10000 6
#340
0!
0)
#350
1!
1)
b10001 6
#360
0!
0)
#370
1!
1)
b10010 6
#380
0!
0)
#390
1!
1)
b10011 6
#400
0!
0)
#410
1!
1)
b10100 6
#420
0!
0)
#430
1!
1)
b10101 6
#440
0!
0)
#450
1!
1)
b10110 6
#460
0!
0)
#470
1!
1)
b10111 6
#480
0!
0)
#490
1!
1)
b11000 6
#500
0!
0)
#510
1!
1)
b11001 6
#520
0!
0)
#530
1!
1)
b11010 6
#540
0!
0)
#550
1!
1)
b11011 6
#560
0!
0)
#570
1!
1)
b11100 6
#580
0!
0)
#590
1!
1)
b11101 6
#600
0!
0)
#610
1!
1)
b11110 6
#620
0!
0)
#630
1!
1)
b11111 6
#640
0!
0)
#650
1!
1)
b100000 6
#660
0!
0)
#670
1!
1)
b100001 6
#680
0!
0)
#690
1!
1)
b100010 6
#700
0!
0)
#710
1!
1)
b100011 6
#720
0!
0)
#730
1!
1)
b100100 6
#740
0!
0)
#750
1!
1)
b100101 6
#760
0!
0)
#770
1!
1)
b100110 6
#780
0!
0)
#790
1!
1)
b100111 6
#800
0!
0)
#810
1!
1)
b101000 6
#820
0!
0)
#830
1!
1)
b101001 6
#840
0!
0)
#850
1!
1)
b101010 6
#860
0!
0)
#870
1!
1)
b101011 6
#880
0!
0)
#890
1!
1)
b101100 6
#900
0!
0)
#910
1!
1)
b101101 6
#920
0!
0)
#930
1!
1)
b101110 6
#940
0!
0)
#950
1!
1)
b101111 6
#960
0!
0)
#970
1!
1)
b110000 6
#980
0!
0)
#990
1!
1)
b110001 6
#1000
0!
0)
#1010
1!
1)
b110010 6
#1020
0!
0)
#1030
1!
1)
b110011 6
#1040
0!
0)
#1050
1!
1)
b110100 6
#1060
0!
0)
#1070
1!
1)
b110101 6
#1080
0!
0)
#1090
1!
1)
b110110 6
#1100
0!
0)
#1110
1!
1)
b110111 6
#1120
0!
0)
#1130
1!
1)
b111000 6
#1140
0!
0)
#1150
1!
1)
b111001 6
#1160
0!
0)
#1170
1!
1)
b111010 6
#1180
0!
0)
#1190
1!
1)
b111011 6
#1200
0!
0)
#1210
1!
1)
b111100 6
#1220
0!
0)
#1230
1!
1)
b111101 6
#1240
0!
0)
#1250
1!
1)
b111110 6
#1260
0!
0)
#1270
1!
1)
b111111 6
#1280
0!
0)
#1290
1!
1)
b1000000 6
1'
17
#1300
0!
0)
#1310
1!
1)
b1000001 6
1;
1$
#1320
0!
0)
#1330
1!
1)
b1000010 6
#1340
0!
0)
#1350
1!
1)
b1000011 6
#1360
0!
0)
#1370
1!
1)
b1000100 6
#1380
0!
0)
#1390
1!
1)
b1000101 6
#1400
0!
0)
#1410
1!
1)
b1000110 6
#1420
0!
0)
#1430
1!
1)
b1000111 6
#1440
0!
0)
#1450
1!
1)
b1001000 6
#1460
0!
0)
#1470
1!
1)
b1001001 6
#1480
0!
0)
#1490
1!
1)
b1001010 6
#1500
0!
0)
#1510
1!
1)
b1001011 6
#1520
0!
0)
#1530
1!
1)
b1001100 6
#1540
0!
0)
#1550
1!
1)
b1001101 6
#1560
0!
0)
#1570
1!
1)
b1001110 6
#1580
0!
0)
#1590
1!
1)
b1001111 6
#1600
0!
0)
#1610
1!
1)
b1010000 6
#1620
0!
0)
#1630
1!
1)
b1010001 6
#1640
0!
0)
#1650
1!
1)
b1010010 6
#1660
0!
0)
#1670
1!
1)
b1010011 6
#1680
0!
0)
#1690
1!
1)
b1010100 6
#1700
0!
0)
#1710
1!
1)
b1010101 6
#1720
0!
0)
#1730
1!
1)
b1010110 6
#1740
0!
0)
#1750
1!
1)
b1010111 6
#1760
0!
0)
#1770
1!
1)
b1011000 6
#1780
0!
0)
#1790
1!
1)
b1011001 6
#1800
0!
0)
#1810
1!
1)
b1011010 6
#1820
0!
0)
#1830
1!
1)
b1011011 6
#1840
0!
0)
#1850
1!
1)
b1011100 6
#1860
0!
0)
#1870
1!
1)
b1011101 6
#1880
0!
0)
#1890
1!
1)
b1011110 6
#1900
0!
0)
#1910
1!
1)
b1011111 6
#1920
0!
0)
#1930
1!
1)
b1100000 6
#1940
0!
0)
#1950
1!
1)
b1100001 6
#1960
0!
0)
#1970
1!
1)
b1100010 6
#1980
0!
0)
#1990
1!
1)
b1100011 6
#2000
0!
0)
#2010
1!
1)
b1100100 6
#2020
0!
0)
#2030
1!
1)
b1100101 6
#2040
0!
0)
#2050
1!
1)
b1100110 6
#2060
0!
0)
#2070
1!
1)
b1100111 6
#2080
0!
0)
#2090
1!
1)
b1101000 6
#2100
0!
0)
#2110
1!
1)
b1101001 6
#2120
0!
0)
#2130
1!
1)
b1101010 6
#2140
0!
0)
#2150
1!
1)
b1101011 6
#2160
0!
0)
#2170
1!
1)
b1101100 6
#2180
0!
0)
#2190
1!
1)
b1101101 6
#2200
0!
0)
#2210
1!
1)
b1101110 6
#2220
0!
0)
#2230
1!
1)
b1101111 6
#2240
0!
0)
#2250
1!
1)
b1110000 6
#2260
0!
0)
#2270
1!
1)
b1110001 6
#2280
0!
0)
#2290
1!
1)
b1110010 6
#2300
0!
0)
#2310
1!
1)
b1110011 6
#2320
0!
0)
#2330
1!
1)
b1110100 6
#2340
0!
0)
#2350
1!
1)
b1110101 6
#2360
0!
0)
#2370
1!
1)
b1110110 6
#2380
0!
0)
#2390
1!
1)
b1110111 6
#2400
0!
0)
#2410
1!
1)
b1111000 6
#2420
0!
0)
#2430
1!
1)
b1111001 6
#2440
0!
0)
#2450
1!
1)
b1111010 6
#2460
0!
0)
#2470
1!
1)
b1111011 6
#2480
0!
0)
#2490
1!
1)
b1111100 6
#2500
0!
0)
#2510
1!
1)
b1111101 6
#2520
0!
0)
#2530
1!
1)
b1111110 6
#2540
0!
0)
#2550
1!
1)
b1111111 6
#2560
0!
0)
#2570
1!
1)
b10000000 6
#2580
0!
0)
#2590
1!
1)
b10000001 6
#2600
0!
0)
#2610
1!
1)
b10000010 6
#2620
0!
0)
#2630
1!
1)
b10000011 6
#2640
0!
0)
#2650
1!
1)
b10000100 6
#2660
0!
0)
#2670
1!
1)
b10000101 6
#2680
0!
0)
#2690
1!
1)
b10000110 6
#2700
0!
0)
#2710
1!
1)
b10000111 6
#2720
0!
0)
#2730
1!
1)
b10001000 6
#2740
0!
0)
#2750
1!
1)
b10001001 6
#2760
0!
0)
#2770
1!
1)
b10001010 6
#2780
0!
0)
#2790
1!
1)
b10001011 6
#2800
0!
0)
#2810
1!
1)
b10001100 6
#2820
0!
0)
#2830
1!
1)
b10001101 6
#2840
0!
0)
#2850
1!
1)
b10001110 6
#2860
0!
0)
#2870
1!
1)
b10001111 6
#2880
0!
0)
#2890
1!
1)
b10010000 6
#2900
0!
0)
#2910
1!
1)
b10010001 6
#2920
0!
0)
#2930
1!
1)
b10010010 6
#2940
0!
0)
#2950
1!
1)
b10010011 6
#2960
0!
0)
#2970
1!
1)
b10010100 6
#2980
0!
0)
#2990
1!
1)
b10010101 6
#3000
0!
0)
#3010
1!
1)
b10010110 6
#3020
0!
0)
#3030
1!
1)
b10010111 6
#3040
0!
0)
#3050
1!
1)
b10011000 6
#3060
0!
0)
#3070
1!
1)
b10011001 6
#3080
0!
0)
#3090
1!
1)
b10011010 6
#3100
0!
0)
#3110
1!
1)
b10011011 6
#3120
0!
0)
#3130
1!
1)
b10011100 6
#3140
0!
0)
#3150
1!
1)
b10011101 6
#3160
0!
0)
#3170
1!
1)
b10011110 6
#3180
0!
0)
#3190
1!
1)
b10011111 6
#3200
0!
0)
#3210
1!
1)
b10100000 6
#3220
0!
0)
#3230
1!
1)
b10100001 6
#3240
0!
0)
#3250
1!
1)
b10100010 6
#3260
0!
0)
#3270
1!
1)
b10100011 6
#3280
0!
0)
#3290
1!
1)
b10100100 6
#3300
0!
0)
#3310
1!
1)
b10100101 6
#3320
0!
0)
#3330
1!
1)
b10100110 6
#3340
0!
0)
#3350
1!
1)
b10100111 6
#3360
0!
0)
#3370
1!
1)
b10101000 6
#3380
0!
0)
#3390
1!
1)
b10101001 6
#3400
0!
0)
#3410
1!
1)
b10101010 6
#3420
0!
0)
#3430
1!
1)
b10101011 6
#3440
0!
0)
#3450
1!
1)
b10101100 6
#3460
0!
0)
#3470
1!
1)
b10101101 6
#3480
0!
0)
#3490
1!
1)
b10101110 6
#3500
0!
0)
#3510
1!
1)
b10101111 6
#3520
0!
0)
#3530
1!
1)
b10110000 6
#3540
0!
0)
#3550
1!
1)
b10110001 6
#3560
0!
0)
#3570
1!
1)
b10110010 6
#3580
0!
0)
#3590
1!
1)
b10110011 6
#3600
0!
0)
#3610
1!
1)
b10110100 6
#3620
0!
0)
#3630
1!
1)
b10110101 6
#3640
0!
0)
#3650
1!
1)
b10110110 6
#3660
0!
0)
#3670
1!
1)
b10110111 6
#3680
0!
0)
#3690
1!
1)
b10111000 6
#3700
0!
0)
#3710
1!
1)
b10111001 6
#3720
0!
0)
#3730
1!
1)
b10111010 6
#3740
0!
0)
#3750
1!
1)
b10111011 6
#3760
0!
0)
#3770
1!
1)
b10111100 6
#3780
0!
0)
#3790
1!
1)
b10111101 6
#3800
0!
0)
#3810
1!
1)
b10111110 6
#3820
0!
0)
#3830
1!
1)
b10111111 6
#3840
0!
0)
#3850
1!
1)
b11000000 6
0'
#3860
0!
0)
#3870
1!
1)
b11000001 6
#3880
0!
0)
#3890
1!
1)
b11000010 6
#3900
0!
0)
#3910
1!
1)
b11000011 6
#3920
0!
0)
#3930
1!
1)
b11000100 6
#3940
0!
0)
#3950
1!
1)
b11000101 6
#3960
0!
0)
#3970
1!
1)
b11000110 6
#3980
0!
0)
#3990
1!
1)
b11000111 6
#4000
0!
0)
#4010
1!
1)
b11001000 6
#4020
0!
0)
#4030
1!
1)
b11001001 6
#4040
0!
0)
#4050
1!
1)
b11001010 6
#4060
0!
0)
#4070
1!
1)
b11001011 6
#4080
0!
0)
#4090
1!
1)
b11001100 6
#4100
0!
0)
#4110
1!
1)
b11001101 6
#4120
0!
0)
#4130
1!
1)
b11001110 6
#4140
0!
0)
#4150
1!
1)
b11001111 6
#4160
0!
0)
#4170
1!
1)
b11010000 6
#4180
0!
0)
#4190
1!
1)
b11010001 6
#4200
0!
0)
#4210
1!
1)
b11010010 6
#4220
0!
0)
#4230
1!
1)
b11010011 6
#4240
0!
0)
#4250
1!
1)
b11010100 6
#4260
0!
0)
#4270
1!
1)
b11010101 6
#4280
0!
0)
#4290
1!
1)
b11010110 6
#4300
0!
0)
#4310
1!
1)
b11010111 6
#4320
0!
0)
#4330
1!
1)
b11011000 6
#4340
0!
0)
#4350
1!
1)
b11011001 6
#4360
0!
0)
#4370
1!
1)
b11011010 6
#4380
0!
0)
#4390
1!
1)
b11011011 6
#4400
0!
0)
#4410
1!
1)
b11011100 6
#4420
0!
0)
#4430
1!
1)
b11011101 6
#4440
0!
0)
#4450
1!
1)
b11011110 6
#4460
0!
0)
#4470
1!
1)
b11011111 6
#4480
0!
0)
#4490
1!
1)
b11100000 6
#4500
0!
0)
#4510
1!
1)
b11100001 6
#4520
0!
0)
#4530
1!
1)
b11100010 6
#4540
0!
0)
#4550
1!
1)
b11100011 6
#4560
0!
0)
#4570
1!
1)
b11100100 6
#4580
0!
0)
#4590
1!
1)
b11100101 6
#4600
0!
0)
#4610
1!
1)
b11100110 6
#4620
0!
0)
#4630
1!
1)
b11100111 6
#4640
0!
0)
#4650
1!
1)
b11101000 6
#4660
0!
0)
#4670
1!
1)
b11101001 6
#4680
0!
0)
#4690
1!
1)
b11101010 6
#4700
0!
0)
#4710
1!
1)
b11101011 6
#4720
0!
0)
#4730
1!
1)
b11101100 6
#4740
0!
0)
#4750
1!
1)
b11101101 6
#4760
0!
0)
#4770
1!
1)
b11101110 6
#4780
0!
0)
#4790
1!
1)
b11101111 6
#4800
0!
0)
#4810
1!
1)
b11110000 6
#4820
0!
0)
#4830
1!
1)
b11110001 6
#4840
0!
0)
#4850
1!
1)
b11110010 6
#4860
0!
0)
#4870
1!
1)
b11110011 6
#4880
0!
0)
#4890
1!
1)
b11110100 6
#4900
0!
0)
#4910
1!
1)
b11110101 6
#4920
0!
0)
#4930
1!
1)
b11110110 6
#4940
0!
0)
#4950
1!
1)
b11110111 6
#4960
0!
0)
#4970
1!
1)
b11111000 6
#4980
0!
0)
#4990
1!
1)
b11111001 6
#5000
0!
0)
#5010
1!
1)
b11111010 6
#5020
0!
0)
#5030
1!
1)
b11111011 6
#5040
0!
0)
#5050
1!
1)
b11111100 6
#5060
0!
0)
#5070
1!
1)
b11111101 6
#5080
0!
0)
#5090
1!
1)
b11111110 6
#5100
0!
0)
#5110
1!
1)
b11111111 6
#5120
0!
0)
#5130
1!
1)
b100000000 6
#5140
0!
0)
#5150
1!
1)
b100000001 6
#5160
0!
0)
#5170
1!
1)
b100000010 6
#5180
0!
0)
#5190
1!
1)
b100000011 6
#5200
0!
0)
#5210
1!
1)
b100000100 6
#5220
0!
0)
#5230
1!
1)
b100000101 6
#5240
0!
0)
#5250
1!
1)
b100000110 6
#5260
0!
0)
#5270
1!
1)
b100000111 6
#5280
0!
0)
#5290
1!
1)
b100001000 6
#5300
0!
0)
#5310
1!
1)
b100001001 6
#5320
0!
0)
#5330
1!
1)
b100001010 6
#5340
0!
0)
#5350
1!
1)
b100001011 6
#5360
0!
0)
#5370
1!
1)
b100001100 6
#5380
0!
0)
#5390
1!
1)
b100001101 6
#5400
0!
0)
#5410
1!
1)
b100001110 6
#5420
0!
0)
#5430
1!
1)
b100001111 6
#5440
0!
0)
#5450
1!
1)
b100010000 6
#5460
0!
0)
#5470
1!
1)
b100010001 6
#5480
0!
0)
#5490
1!
1)
b100010010 6
#5500
0!
0)
#5510
1!
1)
b100010011 6
#5520
0!
0)
#5530
1!
1)
b100010100 6
#5540
0!
0)
#5550
1!
1)
b100010101 6
#5560
0!
0)
#5570
1!
1)
b100010110 6
#5580
0!
0)
#5590
1!
1)
b100010111 6
#5600
0!
0)
#5610
1!
1)
b100011000 6
#5620
0!
0)
#5630
1!
1)
b100011001 6
#5640
0!
0)
#5650
1!
1)
b100011010 6
#5660
0!
0)
#5670
1!
1)
b100011011 6
#5680
0!
0)
#5690
1!
1)
b100011100 6
#5700
0!
0)
#5710
1!
1)
b100011101 6
#5720
0!
0)
#5730
1!
1)
b100011110 6
#5740
0!
0)
#5750
1!
1)
b100011111 6
#5760
0!
0)
#5770
1!
1)
b100100000 6
#5780
0!
0)
#5790
1!
1)
b100100001 6
#5800
0!
0)
#5810
1!
1)
b100100010 6
#5820
0!
0)
#5830
1!
1)
b100100011 6
#5840
0!
0)
#5850
1!
1)
b100100100 6
#5860
0!
0)
#5870
1!
1)
b100100101 6
#5880
0!
0)
#5890
1!
1)
b100100110 6
#5900
0!
0)
#5910
1!
1)
b100100111 6
#5920
0!
0)
#5930
1!
1)
b100101000 6
#5940
0!
0)
#5950
1!
1)
b100101001 6
#5960
0!
0)
#5970
1!
1)
b100101010 6
#5980
0!
0)
#5990
1!
1)
b100101011 6
#6000
0!
0)
#6010
1!
1)
b100101100 6
#6020
0!
0)
#6030
1!
1)
b100101101 6
#6040
0!
0)
#6050
1!
1)
b100101110 6
#6060
0!
0)
#6070
1!
1)
b100101111 6
#6080
0!
0)
#6090
1!
1)
b100110000 6
#6100
0!
0)
#6110
1!
1)
b100110001 6
#6120
0!
0)
#6130
1!
1)
b100110010 6
#6140
0!
0)
#6150
1!
1)
b100110011 6
#6160
0!
0)
#6170
1!
1)
b100110100 6
#6180
0!
0)
#6190
1!
1)
b100110101 6
#6200
0!
0)
#6210
1!
1)
b100110110 6
#6220
0!
0)
#6230
1!
1)
b100110111 6
#6240
0!
0)
#6250
1!
1)
b100111000 6
#6260
0!
0)
#6270
1!
1)
b100111001 6
#6280
0!
0)
#6290
1!
1)
b100111010 6
#6300
0!
0)
#6310
1!
1)
b100111011 6
#6320
0!
0)
#6330
1!
1)
b100111100 6
#6340
0!
0)
#6350
1!
1)
b100111101 6
#6360
0!
0)
#6370
1!
1)
b100111110 6
#6380
0!
0)
#6390
1!
1)
b100111111 6
#6400
0!
0)
#6410
1!
1)
b101000000 6
#6420
0!
0)
#6430
1!
1)
b101000001 6
#6440
0!
0)
#6450
1!
1)
b101000010 6
#6460
0!
0)
#6470
1!
1)
b101000011 6
#6480
0!
0)
#6490
1!
1)
b101000100 6
#6500
0!
0)
#6510
1!
1)
b101000101 6
#6520
0!
0)
#6530
1!
1)
b101000110 6
#6540
0!
0)
#6550
1!
1)
b101000111 6
#6560
0!
0)
#6570
1!
1)
b101001000 6
#6580
0!
0)
#6590
1!
1)
b101001001 6
#6600
0!
0)
#6610
1!
1)
b101001010 6
#6620
0!
0)
#6630
1!
1)
b101001011 6
#6640
0!
0)
#6650
1!
1)
b101001100 6
#6660
0!
0)
#6670
1!
1)
b101001101 6
#6680
0!
0)
#6690
1!
1)
b101001110 6
#6700
0!
0)
#6710
1!
1)
b101001111 6
#6720
0!
0)
#6730
1!
1)
b101010000 6
#6740
0!
0)
#6750
1!
1)
b101010001 6
#6760
0!
0)
#6770
1!
1)
b101010010 6
#6780
0!
0)
#6790
1!
1)
b101010011 6
#6800
0!
0)
#6810
1!
1)
b101010100 6
#6820
0!
0)
#6830
1!
1)
b101010101 6
#6840
0!
0)
#6850
1!
1)
b101010110 6
#6860
0!
0)
#6870
1!
1)
b101010111 6
#6880
0!
0)
#6890
1!
1)
b101011000 6
#6900
0!
0)
#6910
1!
1)
b101011001 6
#6920
0!
0)
#6930
1!
1)
b101011010 6
#6940
0!
0)
#6950
1!
1)
b101011011 6
#6960
0!
0)
#6970
1!
1)
b101011100 6
#6980
0!
0)
#6990
1!
1)
b101011101 6
#7000
0!
0)
#7010
1!
1)
b101011110 6
#7020
0!
0)
#7030
1!
1)
b101011111 6
#7040
0!
0)
#7050
1!
1)
b101100000 6
#7060
0!
0)
#7070
1!
1)
b101100001 6
#7080
0!
0)
#7090
1!
1)
b101100010 6
#7100
0!
0)
#7110
1!
1)
b101100011 6
#7120
0!
0)
#7130
1!
1)
b101100100 6
#7140
0!
0)
#7150
1!
1)
b101100101 6
#7160
0!
0)
#7170
1!
1)
b101100110 6
#7180
0!
0)
#7190
1!
1)
b101100111 6
#7200
0!
0)
#7210
1!
1)
b101101000 6
#7220
0!
0)
#7230
1!
1)
b101101001 6
#7240
0!
0)
#7250
1!
1)
b101101010 6
#7260
0!
0)
#7270
1!
1)
b101101011 6
#7280
0!
0)
#7290
1!
1)
b101101100 6
#7300
0!
0)
#7310
1!
1)
b101101101 6
#7320
0!
0)
#7330
1!
1)
b101101110 6
#7340
0!
0)
#7350
1!
1)
b101101111 6
#7360
0!
0)
#7370
1!
1)
b101110000 6
#7380
0!
0)
#7390
1!
1)
b101110001 6
#7400
0!
0)
#7410
1!
1)
b101110010 6
#7420
0!
0)
#7430
1!
1)
b101110011 6
#7440
0!
0)
#7450
1!
1)
b101110100 6
#7460
0!
0)
#7470
1!
1)
b101110101 6
#7480
0!
0)
#7490
1!
1)
b101110110 6
#7500
0!
0)
#7510
1!
1)
b101110111 6
#7520
0!
0)
#7530
1!
1)
b101111000 6
#7540
0!
0)
#7550
1!
1)
b101111001 6
#7560
0!
0)
#7570
1!
1)
b101111010 6
#7580
0!
0)
#7590
1!
1)
b101111011 6
#7600
0!
0)
#7610
1!
1)
b101111100 6
#7620
0!
0)
#7630
1!
1)
b101111101 6
#7640
0!
0)
#7650
1!
1)
b101111110 6
#7660
0!
0)
#7670
1!
1)
b101111111 6
#7680
0!
0)
#7690
1!
1)
b110000000 6
#7700
0!
0)
#7710
1!
1)
b110000001 6
#7720
0!
0)
#7730
1!
1)
b110000010 6
#7740
0!
0)
#7750
1!
1)
b110000011 6
#7760
0!
0)
#7770
1!
1)
b110000100 6
#7780
0!
0)
#7790
1!
1)
b110000101 6
#7800
0!
0)
#7810
1!
1)
b110000110 6
#7820
0!
0)
#7830
1!
1)
b110000111 6
#7840
0!
0)
#7850
1!
1)
b110001000 6
#7860
0!
0)
#7870
1!
1)
b110001001 6
#7880
0!
0)
#7890
1!
1)
b110001010 6
#7900
0!
0)
#7910
1!
1)
b110001011 6
#7920
0!
0)
#7930
1!
1)
b110001100 6
#7940
0!
0)
#7950
1!
1)
b110001101 6
#7960
0!
0)
#7970
1!
1)
b110001110 6
#7980
0!
0)
#7990
1!
1)
b110001111 6
#8000
0!
0)
#8010
1!
1)
b110010000 6
#8020
0!
0)
#8030
1!
1)
b110010001 6
#8040
0!
0)
#8050
1!
1)
b110010010 6
#8060
0!
0)
#8070
1!
1)
b110010011 6
#8080
0!
0)
#8090
1!
1)
b110010100 6
#8100
0!
0)
#8110
1!
1)
b110010101 6
#8120
0!
0)
#8130
1!
1)
b110010110 6
#8140
0!
0)
#8150
1!
1)
b110010111 6
#8160
0!
0)
#8170
1!
1)
b110011000 6
#8180
0!
0)
#8190
1!
1)
b110011001 6
#8200
0!
0)
#8210
1!
1)
b110011010 6
#8220
0!
0)
#8230
1!
1)
b110011011 6
#8240
0!
0)
#8250
1!
1)
b110011100 6
#8260
0!
0)
#8270
1!
1)
b110011101 6
#8280
0!
0)
#8290
1!
1)
b110011110 6
#8300
0!
0)
#8310
1!
1)
b110011111 6
#8320
0!
0)
#8330
1!
1)
b110100000 6
#8340
0!
0)
#8350
1!
1)
b110100001 6
#8360
0!
0)
#8370
1!
1)
b110100010 6
#8380
0!
0)
#8390
1!
1)
b110100011 6
#8400
0!
0)
#8410
1!
1)
b110100100 6
#8420
0!
0)
#8430
1!
1)
b110100101 6
#8440
0!
0)
#8450
1!
1)
b110100110 6
#8460
0!
0)
#8470
1!
1)
b110100111 6
#8480
0!
0)
#8490
1!
1)
b110101000 6
#8500
0!
0)
#8510
1!
1)
b110101001 6
#8520
0!
0)
#8530
1!
1)
b110101010 6
#8540
0!
0)
#8550
1!
1)
b110101011 6
#8560
0!
0)
#8570
1!
1)
b110101100 6
#8580
0!
0)
#8590
1!
1)
b110101101 6
#8600
0!
0)
#8610
1!
1)
b110101110 6
#8620
0!
0)
#8630
1!
1)
b110101111 6
#8640
0!
0)
#8650
1!
1)
b110110000 6
#8660
0!
0)
#8670
1!
1)
b110110001 6
#8680
0!
0)
#8690
1!
1)
b110110010 6
#8700
0!
0)
#8710
1!
1)
b110110011 6
#8720
0!
0)
#8730
1!
1)
b110110100 6
#8740
0!
0)
#8750
1!
1)
b110110101 6
#8760
0!
0)
#8770
1!
1)
b110110110 6
#8780
0!
0)
#8790
1!
1)
b110110111 6
#8800
0!
0)
#8810
1!
1)
b110111000 6
#8820
0!
0)
#8830
1!
1)
b110111001 6
#8840
0!
0)
#8850
1!
1)
b110111010 6
#8860
0!
0)
#8870
1!
1)
b110111011 6
#8880
0!
0)
#8890
1!
1)
b110111100 6
#8900
0!
0)
#8910
1!
1)
b110111101 6
#8920
0!
0)
#8930
1!
1)
b110111110 6
#8940
0!
0)
#8950
1!
1)
b110111111 6
#8960
0!
0)
#8970
1!
1)
b111000000 6
#8980
0!
0)
#8990
1!
1)
b111000001 6
#9000
0!
0)
